pysecret/__init__.py
pysecret/_version.py
pysecret/compat.py
pysecret/env.py
pysecret/helper.py
pysecret/js.py
pysecret/js_helper.py
pysecret/paths.py
pysecret/sh.py
pysecret/sh_helper.py
pysecret/singleton.py
pysecret/singleton_alternative.py
pysecret/aws/__init__.py
pysecret/aws/kms.py
pysecret/aws/main.py
pysecret/aws/parameter_store.py
pysecret/aws/secret_manager.py
pysecret/aws/tagging.py
pysecret/docs/__init__.py
pysecret/tests/__init__.py
pysecret/tests/covtest.py
pysecret/tests/paths.py
pysecret-2.2.4.dist-info/AUTHORS.rst
pysecret-2.2.4.dist-info/LICENSE.txt
pysecret-2.2.4.dist-info/METADATA
pysecret-2.2.4.dist-info/WHEEL
pysecret-2.2.4.dist-info/top_level.txt
pysecret-2.2.4.dist-info/RECORD
