Metadata-Version: 2.1
Name: pysecret
Version: 2.2.4
Summary: utility tool that load secret information safely.
Home-page: https://github.com/MacHu-GWU/pysecret-project
Download-URL: https://pypi.python.org/pypi/pysecret/2.2.4#downloads
Author: Sanhe Hu
Author-email: husanhe@gmail.com
Maintainer: Unknown
License: MIT
Platform: Windows
Platform: MacOS
Platform: Unix
Classifier: Development Status :: 4 - Beta
Classifier: Intended Audience :: Developers
Classifier: License :: OSI Approved :: MIT License
Classifier: Natural Language :: English
Classifier: Operating System :: Microsoft :: Windows
Classifier: Operating System :: MacOS
Classifier: Operating System :: Unix
Classifier: Programming Language :: Python :: 3 :: Only
Classifier: Programming Language :: Python :: 3.7
Classifier: Programming Language :: Python :: 3.8
Classifier: Programming Language :: Python :: 3.9
Classifier: Programming Language :: Python :: 3.10
Classifier: Programming Language :: Python :: 3.11
License-File: LICENSE.txt
License-File: AUTHORS.rst
Requires-Dist: cached-property >=1.5.2 ; python_version < "3.8"
Provides-Extra: docs
Requires-Dist: sphinx ==4.3.0 ; extra == 'docs'
Requires-Dist: sphinx-inline-tabs ==2021.8.17b10 ; extra == 'docs'
Requires-Dist: sphinx-jinja ==1.1.1 ; extra == 'docs'
Requires-Dist: sphinx-copybutton ==0.4.0 ; extra == 'docs'
Requires-Dist: rstobj ==0.0.7 ; extra == 'docs'
Requires-Dist: docfly ==1.0.2 ; extra == 'docs'
Requires-Dist: furo ==2021.8.31 ; extra == 'docs'
Provides-Extra: tests
Requires-Dist: pytest ; extra == 'tests'
Requires-Dist: pytest-cov ; extra == 'tests'
